examples/ii_search_4b/__init__.py
examples/ii_search_4b/configs.py
examples/ii_search_4b/gradio_demo.py
examples/ii_search_4b/search_assistant.py
examples/ii_search_4b/core/__init__.py
examples/ii_search_4b/core/code_executor.py
examples/ii_search_4b/core/google_search_client.py
examples/ii_search_4b/core/medical_search_server.py
examples/ii_search_4b/core/search_client.py
ii_researcher/__init__.py
ii_researcher/cli.py
ii_researcher/config.py
ii_researcher/reasoning/__init__.py
ii_researcher/reasoning/agent.py
ii_researcher/reasoning/config.py
ii_researcher/reasoning/utils.py
ii_researcher/reasoning/builders/report.py
ii_researcher/reasoning/clients/__init__.py
ii_researcher/reasoning/clients/openai_client.py
ii_researcher/reasoning/models/__init__.py
ii_researcher/reasoning/models/action.py
ii_researcher/reasoning/models/output.py
ii_researcher/reasoning/models/trace.py
ii_researcher/reasoning/tools/__init__.py
ii_researcher/reasoning/tools/base.py
ii_researcher/reasoning/tools/registry.py
ii_researcher/reasoning/tools/tool_history.py
ii_researcher/reasoning/tools/web_scraper.py
ii_researcher/reasoning/tools/web_search.py
ii_researcher/tool_clients/__init__.py
ii_researcher/tool_clients/scrape_client.py
ii_researcher/tool_clients/search_client.py
ii_researcher/tool_clients/compressor/__init__.py
ii_researcher/tool_clients/compressor/base.py
ii_researcher/tool_clients/compressor/compressor_client.py
ii_researcher/tool_clients/compressor/context_compressor.py
ii_researcher/tool_clients/compressor/embedding_compressor.py
ii_researcher/tool_clients/compressor/llm_compressor.py
ii_researcher/tool_clients/scraper/__init__.py
ii_researcher/tool_clients/scraper/scraper.py
ii_researcher/tool_clients/scraper/utils.py
ii_researcher/tool_clients/scraper/beautiful_soup/__init__.py
ii_researcher/tool_clients/scraper/beautiful_soup/beautiful_soup.py
ii_researcher/tool_clients/scraper/browser/__init__.py
ii_researcher/tool_clients/scraper/browser/browser.py
mseep_ii_researcher-0.1.6.dist-info/licenses/LICENSE
mseep_ii_researcher-0.1.6.dist-info/METADATA
mseep_ii_researcher-0.1.6.dist-info/WHEEL
mseep_ii_researcher-0.1.6.dist-info/top_level.txt
mseep_ii_researcher-0.1.6.dist-info/RECORD
