Metadata-Version: 2.4
Name: mseep-ii-researcher
Version: 0.1.6
Summary: II Researcher Package
Author-email: mseep <support@skydeck.ai>
License:                                  Apache License
Requires-Python: >=3.8
License-File: LICENSE
Requires-Dist: requests
Requires-Dist: baml-py==0.77.0
Requires-Dist: pydantic>=2.0.0
Requires-Dist: fastapi>=0.100.0
Requires-Dist: requests>=2.32.3
Requires-Dist: bs4>=0.0.2
Requires-Dist: markdownify>=1.0.0
Requires-Dist: readability-lxml>=0.8.1
Requires-Dist: lxml[html-clean]>=5.3.1
Requires-Dist: tavily-python>=0.5.1
Requires-Dist: colorama>=0.4.6
Requires-Dist: langchain-community>=0.3.18
Requires-Dist: yt-dlp>=2025.2.19
Requires-Dist: click>=8.1.8
Requires-Dist: langchain-openai>=0.3.7
Requires-Dist: pymupdf>=1.25.3
Requires-Dist: markdown>=3.7
Requires-Dist: clean-text[gpl]>=0.6.0
Requires-Dist: litellm[proxy]>=1.63.6
Requires-Dist: uvicorn>=0.29.0
Requires-Dist: baml-cli>=0.1.0
Provides-Extra: dev
Requires-Dist: pytest; extra == "dev"
Requires-Dist: black; extra == "dev"
Requires-Dist: isort; extra == "dev"
Requires-Dist: flake8; extra == "dev"
Dynamic: license-file
